project_template.py
project_template-0.1.0.dist-info/LICENSE
project_template-0.1.0.dist-info/WHEEL
project_template-0.1.0.dist-info/METADATA
project_template-0.1.0.dist-info/RECORD
