Metadata-Version: 2.1
Name: project-template
Version: 0.1.0
Summary: 
Home-page: https://github.com/thejohnfreeman/project-template-python/
License: ISC
Author: John Freeman
Author-email: jfreeman08@gmail.com
Requires-Python: >=3.6-dev,<4.0
Classifier: License :: OSI Approved
Classifier: Programming Language :: Python :: 3
Classifier: Programming Language :: Python :: 3.6
Classifier: Programming Language :: Python :: 3.7
Provides-Extra: docs
Requires-Dist: sphinx (>=1.8,<2.0); extra == "docs"
Requires-Dist: sphinx_rtd_theme (>=0.4.3,<0.5.0); extra == "docs"
Requires-Dist: toml (>=0.10.0,<0.11.0); extra == "docs"
Project-URL: Documentation, https://project-template-python.readthedocs.io/
Project-URL: Repository, https://github.com/thejohnfreeman/project-template-python/
